mattia80511/__init__.py
mattia80511-0.1.dist-info/METADATA
mattia80511-0.1.dist-info/WHEEL
mattia80511-0.1.dist-info/top_level.txt
mattia80511-0.1.dist-info/RECORD
