Metadata-Version: 2.1
Name: mattia80511
Version: 0.1
Summary: A personal utility package.
Home-page: UNKNOWN
Author-email: mattai0311@gmail.com
License: UNKNOWN
Platform: UNKNOWN
Classifier: Programming Language :: Python :: 3
Requires-Python: >=3.6
